{
  "main": {
    "id": "5fa247930169a3c9",
    "type": "split",
    "children": [
      {
        "id": "fa23fc2fc715db3a",
        "type": "tabs",
        "children": [
          {
            "id": "66ce1bfa6f9d67a4",
            "type": "leaf",
            "state": {
              "type": "markdown",
              "state": {
                "file": "Java/class_and_instance/class_and_instance.md",
                "mode": "source",
                "backlinks": false,
                "source": false
              }
            }
          }
        ]
      }
    ],
    "direction": "vertical"
  },
  "left": {
    "id": "c87f4d3a25d5272e",
    "type": "split",
    "children": [
      {
        "id": "9c993f0eab604fb7",
        "type": "tabs",
        "children": [
          {
            "id": "67dd981fc3075972",
            "type": "leaf",
            "state": {
              "type": "file-explorer",
              "state": {
                "sortOrder": "alphabetical"
              }
            }
          },
          {
            "id": "ba830c85cb50b926",
            "type": "leaf",
            "state": {
              "type": "search",
              "state": {
                "query": "",
                "matchingCase": false,
                "explainSearch": false,
                "collapseAll": false,
                "extraContext": false,
                "sortOrder": "alphabetical"
              }
            }
          },
          {
            "id": "a2ed4fc3df385625",
            "type": "leaf",
            "state": {
              "type": "bookmarks",
              "state": {}
            }
          }
        ]
      }
    ],
    "direction": "horizontal",
    "width": 224.5
  },
  "right": {
    "id": "e54cca2b1a4710d6",
    "type": "split",
    "children": [
      {
        "id": "ccae3721b5e0b4dc",
        "type": "tabs",
        "children": [
          {
            "id": "0a870261410b2a74",
            "type": "leaf",
            "state": {
              "type": "backlink",
              "state": {
                "file": "Java/class_and_instance/class_and_instance.md",
                "collapseAll": false,
                "extraContext": false,
                "sortOrder": "alphabetical",
                "showSearch": false,
                "searchQuery": "",
                "backlinkCollapsed": false,
                "unlinkedCollapsed": true
              }
            }
          },
          {
            "id": "49d59b676895bb57",
            "type": "leaf",
            "state": {
              "type": "tag",
              "state": {
                "sortOrder": "frequency",
                "useHierarchy": true
              }
            }
          },
          {
            "id": "4cb8d4176b15c5e5",
            "type": "leaf",
            "state": {
              "type": "outgoing-link",
              "state": {
                "file": "Java/class_and_instance/class_and_instance.md",
                "linksCollapsed": false,
                "unlinkedCollapsed": true
              }
            }
          },
          {
            "id": "db7c054552e9bbec",
            "type": "leaf",
            "state": {
              "type": "outline",
              "state": {
                "file": "Java/class_and_instance/class_and_instance.md"
              }
            }
          },
          {
            "id": "6497d55a24dde659",
            "type": "leaf",
            "state": {
              "type": "advanced-tables-toolbar",
              "state": {}
            }
          }
        ],
        "currentTab": 3
      },
      {
        "id": "e9da477ccbd30d11",
        "type": "tabs",
        "children": [
          {
            "id": "7a5d19f07e005f37",
            "type": "leaf",
            "state": {
              "type": "empty",
              "state": {}
            }
          }
        ]
      }
    ],
    "direction": "horizontal",
    "width": 200
  },
  "left-ribbon": {
    "hiddenItems": {
      "templater-obsidian:Templater": false,
      "table-editor-obsidian:Advanced Tables Toolbar": false,
      "switcher:打开快速切换": false,
      "graph:查看关系图谱": false,
      "canvas:新建白板": false,
      "daily-notes:打开/创建今天的日记": false,
      "command-palette:打开命令面板": false,
      "workspaces:管理工作区布局": false
    }
  },
  "active": "67dd981fc3075972",
  "lastOpenFiles": [
    "Java/jvm_base/jvm_base.md",
    "Java/class_and_instance/class_and_instance.md",
    "Java/thread/thread.md",
    "Java/concurrency/concurrency.md",
    "Java/memory_model/memory_model.md",
    "Pattern/single/single.md",
    "读书笔记/MySQL/note/并发.md",
    "OS/内存管理.md",
    "Java/grammer/grammer.md",
    "Database/concurrency/concurrency.md",
    "读书笔记/MySQL/note/日志.md",
    "读书笔记/MySQL/note/查询.md",
    "读书笔记/MySQL/note/锁定读加锁机制.md",
    "读书笔记/MySQL/note/加锁机制.md",
    "读书笔记/MySQL/note/数据存储.md",
    "OS/异常 & 中断.md",
    "OS/文件系统.md",
    "OS/deadlock/deadlock.md",
    "OS/网络 IO.md",
    "OS/image/非阻塞 IO-多路复用.jpg",
    "OS/image/io_file_transfer_read+write.webp",
    "OS/image/异步 IO.jpg",
    "OS/image/非阻塞 IO.jpg",
    "OS/image/阻塞 IO.jpg",
    "OS/image/io_without dma.webp",
    "OS/image/io_with dma.webp",
    "OS/image/IO2.webp",
    "OS/image/io_big_file_transfer.webp",
    "OS/image/io_file_transfer_mmap+write.webp",
    "image/io_model.jpg.md",
    "image",
    "Java/gc/gc.md",
    "Java/advance/advance.md",
    "OS/ostep/virtualization/memory/segmentation.md",
    "OS/ostep/virtualization/memory/mechanism_address translation.md",
    "OS/ostep/virtualization/memory/summary_hardware support.md",
    "OS/ostep/virtualization/memory/abstraction_address spaces.md"
  ]
}